./.gitignore
./LICENSE
./PKG-INFO
./README.md
./mcp_server_fider.py
./pyproject.toml
./.claude/settings.local.json
mcp_fider-2025.6.27.170000.dist-info/METADATA
mcp_fider-2025.6.27.170000.dist-info/WHEEL
mcp_fider-2025.6.27.170000.dist-info/entry_points.txt
mcp_fider-2025.6.27.170000.dist-info/licenses/LICENSE
mcp_fider-2025.6.27.170000.dist-info/RECORD
