Metadata-Version: 2.4
Name: mcp-fider
Version: 2025.6.27.170000
Summary: MCP (Model Context Protocol) server for Fider API integration
Project-URL: Homepage, https://github.com/ringostat/fider-mcp
Project-URL: Issues, https://github.com/ringostat/fider-mcp/issues
Author-email: Ringostat <info@ringostat.com>
License: MIT
License-File: LICENSE
Requires-Python: >=3.8
Requires-Dist: aiohttp>=3.9.0
